Demo.py
Demo/icons/Demo.png
Demo/icons/Drawing.png
Demo/icons/Graphviz.png
Demo/icons/Obj.png
Demo/icons/ObjectModel.png
Demo/icons/Y3A.png
ObjectModelFramework/ObjectModelFramework.py
ObjectModelFramework/__init__.py
ObjectModelFramework/_version.py
ObjectModelFramework-0.0.23.dist-info/LICENSE
ObjectModelFramework-0.0.23.dist-info/METADATA
ObjectModelFramework-0.0.23.dist-info/WHEEL
ObjectModelFramework-0.0.23.dist-info/top_level.txt
ObjectModelFramework-0.0.23.dist-info/RECORD
